[
    {
        "admissionid": 1646,
        "orderid": 38371,
        "ordercategoryid": 9,
        "ordercategoryname": "Diagnostic Imaging",
        "itemid": 5417,
        "item": "Arterial Blood Gas",
        "registeredat": "2000-01-01 00:07:35.644000",
        "registeredby": "Nurses",
        "dataset": "Procedure Order Items Dataset"
    },
    {
        "admissionid": 8641,
        "orderid": 23833,
        "ordercategoryid": 10,
        "ordercategoryname": "ICU Scoring",
        "itemid": 6780,
        "item": "Wound Dressing",
        "registeredat": "2000-01-01 00:06:06.678000",
        "registeredby": "Nurses",
        "dataset": "Procedure Order Items Dataset"
    },
    {
        "admissionid": 2642,
        "orderid": 63286,
        "ordercategoryid": 2,
        "ordercategoryname": "Emergency Procedures",
        "itemid": 1959,
        "item": "Central Line Insertion",
        "registeredat": "2000-01-01 00:15:50.853000",
        "registeredby": "Technicians",
        "dataset": "Procedure Order Items Dataset"
    },
    {
        "admissionid": 6867,
        "orderid": 35603,
        "ordercategoryid": 8,
        "ordercategoryname": "Diagnostic Imaging",
        "itemid": 3702,
        "item": "Central Line Insertion",
        "registeredat": "2000-01-01 00:06:14.682000",
        "registeredby": "Nurses",
        "dataset": "Procedure Order Items Dataset"
    },
    {
        "admissionid": 2642,
        "orderid": 93570,
        "ordercategoryid": 6,
        "ordercategoryname": "Emergency Procedures",
        "itemid": 3563,
        "item": "Central Line Insertion",
        "registeredat": "2000-01-01 00:16:10.222000",
        "registeredby": "Nurses",
        "dataset": "Procedure Order Items Dataset"
    },
    {
        "admissionid": 9061,
        "orderid": 60359,
        "ordercategoryid": 6,
        "ordercategoryname": "Diagnostic Imaging",
        "itemid": 3696,
        "item": "Chest X-Ray",
        "registeredat": "2000-01-01 00:04:50.900000",
        "registeredby": "Technicians",
        "dataset": "Procedure Order Items Dataset"
    },
    {
        "admissionid": 3442,
        "orderid": 79970,
        "ordercategoryid": 9,
        "ordercategoryname": "ICU Scoring",
        "itemid": 7703,
        "item": "Central Line Insertion",
        "registeredat": "2000-01-01 00:06:46.822000",
        "registeredby": "Physicians",
        "dataset": "Procedure Order Items Dataset"
    },
    {
        "admissionid": 1876,
        "orderid": 39741,
        "ordercategoryid": 9,
        "ordercategoryname": "Emergency Procedures",
        "itemid": 9608,
        "item": "Chest X-Ray",
        "registeredat": "2000-01-01 00:01:26.909000",
        "registeredby": "Technicians",
        "dataset": "Procedure Order Items Dataset"
    },
    {
        "admissionid": 1817,
        "orderid": 0,
        "ordercategoryid": 0,
        "ordercategoryname": "0",
        "itemid": 0,
        "item": "Default Procedure",
        "registeredat": "0",
        "registeredby": "0",
        "dataset": "Procedure Order Items Dataset"
    },
    {
        "admissionid": 5791,
        "orderid": 0,
        "ordercategoryid": 0,
        "ordercategoryname": "0",
        "itemid": 0,
        "item": "Default Procedure",
        "registeredat": "0",
        "registeredby": "0",
        "dataset": "Procedure Order Items Dataset"
    },
    {
        "admissionid": 2769,
        "orderid": 0,
        "ordercategoryid": 0,
        "ordercategoryname": "0",
        "itemid": 0,
        "item": "Default Procedure",
        "registeredat": "0",
        "registeredby": "0",
        "dataset": "Procedure Order Items Dataset"
    }
]